pygitup/__init__.py
pygitup/generic.py
pygitup/git_adapter.py
pygitup/main_pygitup.py
pygitup/programs.py
pygitup/update.py
py_git_backup-0.0.3.dist-info/METADATA
py_git_backup-0.0.3.dist-info/WHEEL
py_git_backup-0.0.3.dist-info/entry_points.txt
py_git_backup-0.0.3.dist-info/top_level.txt
py_git_backup-0.0.3.dist-info/RECORD
