Metadata-Version: 2.2
Name: py-git-backup
Version: 0.0.3
Summary: build scripts for firmware projects
Home-page: 
Author: Richard Peschke
Author-email: peschke@hawaii.edu
Classifier: Programming Language :: Python :: 3
Classifier: License :: OSI Approved :: MIT License
Classifier: Operating System :: OS Independent
Requires-Python: >=3.8
Dynamic: author
Dynamic: author-email
Dynamic: classifier
Dynamic: description
Dynamic: description-content-type
Dynamic: requires-python
Dynamic: summary
